.travis.yml
AUTHORS.rst
CHANGES.rst
Procfile
README.rst
example.py
requirements.txt
setup.py
Flask_Sillywalk.egg-info/PKG-INFO
Flask_Sillywalk.egg-info/SOURCES.txt
Flask_Sillywalk.egg-info/dependency_links.txt
Flask_Sillywalk.egg-info/not-zip-safe
Flask_Sillywalk.egg-info/requires.txt
Flask_Sillywalk.egg-info/top_level.txt
flask_sillywalk/__init__.py
flask_sillywalk/compat.py
flask_sillywalk/sillywalk.py
flask_sillywalk/tests/__init__.py
flask_sillywalk/tests/test_sillywalk.py