Metadata-Version: 1.1
Name: Flask-Sillywalk
Version: 2.1
Summary: So you want to implement an auto-documenting API?
Home-page: https://github.com/hobbeswalsh/flask-sillywalk
Author: Robin Walsh & Harvey Rogers
Author-email: rob.walsh@gmail.com
License: BSD
Platform: any
Classifier: Environment :: Web Environment
Classifier: Intended Audience :: Developers
Classifier: License :: OSI Approved :: BSD License
Classifier: Operating System :: OS Independent
Classifier: Programming Language :: Python :: 3
Classifier: Topic :: Internet :: WWW/HTTP :: Dynamic Content
Classifier: Topic :: Software Development :: Libraries :: Python Modules
